farmhash.cpython-313-darwin.so
cityhash.cpython-313-darwin.so
cityhashcrc.cpython-313-darwin.so
cityhash-0.4.10.dist-info/RECORD
cityhash-0.4.10.dist-info/WHEEL
cityhash-0.4.10.dist-info/top_level.txt
cityhash-0.4.10.dist-info/METADATA
cityhash-0.4.10.dist-info/licenses/LICENSE
