Metadata-Version: 2.1
Name: cityhash
Version: 0.4.10
Summary: Python bindings for CityHash and FarmHash
Home-page: https://github.com/escherba/python-cityhash
Download-URL: https://github.com/escherba/python-cityhash/tarball/master/0.4.10
Author: Eugene Scherba
Author-email: escherba+cityhash@gmail.com
License: MIT
Keywords: google,hash,hashing,cityhash,farmhash,murmurhash,cython
Classifier: Development Status :: 5 - Production/Stable
Classifier: Intended Audience :: Developers
Classifier: Intended Audience :: Science/Research
Classifier: License :: OSI Approved :: MIT License
Classifier: Operating System :: OS Independent
Classifier: Programming Language :: C++
Classifier: Programming Language :: Cython
Classifier: Programming Language :: Python :: 3.6
Classifier: Programming Language :: Python :: 3.7
Classifier: Programming Language :: Python :: 3.8
Classifier: Programming Language :: Python :: 3.9
Classifier: Programming Language :: Python :: 3.10
Classifier: Programming Language :: Python :: 3.11
Classifier: Programming Language :: Python :: 3.12
Classifier: Programming Language :: Python :: 3.13
Classifier: Topic :: Scientific/Engineering :: Information Analysis
Classifier: Topic :: Software Development :: Libraries
Classifier: Topic :: System :: Distributed Computing
Requires-Python: >=3.6
License-File: LICENSE
